minictl-0.1.9.dist-info/METADATA
minictl-0.1.9.dist-info/WHEEL
minictl-0.1.9.dist-info/licenses/LICENSE
minictl/__init__.py
minictl/__init__.pyi
minictl/py.typed
minictl/minictl.pypy39-pp73-ppc_64-linux-gnu.so
minictl-0.1.9.dist-info/RECORD
