Metadata-Version: 2.4
Name: minictl
Version: 0.1.9
Classifier: Programming Language :: Rust
Classifier: Programming Language :: Python :: Implementation :: CPython
Classifier: Programming Language :: Python :: Implementation :: PyPy
Classifier: Operating System :: POSIX :: Linux
Classifier: Operating System :: MacOS
Classifier: Operating System :: Microsoft :: Windows :: Windows 8
Classifier: Operating System :: Microsoft :: Windows :: Windows 8.1
Classifier: Operating System :: Microsoft :: Windows :: Windows 10
Classifier: Operating System :: Microsoft :: Windows :: Windows 11
Classifier: Intended Audience :: Education
Classifier: Intended Audience :: Science/Research
Classifier: License :: OSI Approved :: MIT License
Requires-Dist: pytest ; extra == 'dev'
Requires-Dist: black ; extra == 'dev'
Provides-Extra: dev
License-File: LICENSE
License-File: LICENSE
Summary: A small model checker for Computational Tree Logic
Keywords: model-checking,CTL,kripke-structure
Home-Page: https://github.com/JJWRoeloffs/minictl
License: MIT
Requires-Python: >=3.9
Project-URL: Homepage, https://github.com/JJWRoeloffs/minictl
Project-URL: Bug Tracker, https://github.com/JJWRoeloffs/minictl/issues
